{
    "languages": {
        "ID": {
            "0x409": "english",
            "0x419" : "russian",
            "0x422" : "ukranian"
        }, 
        "layouts": {
            "english": [
                "~!@#$%^&*()_+", "`1234567890-=",
                "QWERTYUIOP{}ASDFGHJKL:'ZXCVBNM<>?", 
                "qwertyuiop[]asdfghjkl;'zxcvbnm,./"],
            "ukranian": [
                "вВі!'вДЦ;%:?*()_+", "'1234567890-=",
                "–Щ–¶–£–Ъ–Х–Э–У–®–©–Ч–•–З–§–Ж–Т–Р–Я–†–Ю–Ы–Ф–Ц–Д–ѓ–І–°–Ь–Ш–Ґ–ђ–С–Ѓ,",
                "–є—Ж—Г–Ї–µ–љ–≥—И—Й–Ј—Е—Ч—Д—Ц–≤–∞–њ—А–Њ–ї–і–ґ—Ф—П—З—Б–Љ–Є—В—М–±—О."],
            "russian": [
                "–Б!'вДЦ;%:?*()_+", "—С1234567890-=",
                "–Щ–¶–£–Ъ–Х–Э–У–®–©–Ч–•–™–§–Ђ–Т–Р–Я–†–Ю–Ы–Ф–Ц–≠–ѓ–І–°–Ь–Ш–Ґ–ђ–С–Ѓ,",
                "–є—Ж—Г–Ї–µ–љ–≥—И—Й–Ј—Е—К—Д—Л–≤–∞–њ—А–Њ–ї–і–ґ—Н—П—З—Б–Љ–Є—В—М–±—О."
            ]
        }
    }
}